haystack_pydoc_tools/__about__.py
haystack_pydoc_tools/__init__.py
haystack_pydoc_tools/loaders.py
haystack_pydoc_tools/renderers.py
haystack_pydoc_tools-0.6.3.dist-info/METADATA
haystack_pydoc_tools-0.6.3.dist-info/WHEEL
haystack_pydoc_tools-0.6.3.dist-info/licenses/LICENSE
haystack_pydoc_tools-0.6.3.dist-info/RECORD
