Metadata-Version: 2.4
Name: haystack-pydoc-tools
Version: 0.6.3
Summary: Pydoc custom tools for Haystack docs
Project-URL: Documentation, https://github.com/unknown/haystack-pydoc-tools#readme
Project-URL: Issues, https://github.com/unknown/haystack-pydoc-tools/issues
Project-URL: Source, https://github.com/unknown/haystack-pydoc-tools
Author-email: Massimiliano Pippi <mpippi@gmail.com>
License-Expression: Apache-2.0
License-File: LICENSE
Classifier: Development Status :: 4 - Beta
Classifier: License :: OSI Approved :: Apache Software License
Classifier: Programming Language :: Python
Classifier: Programming Language :: Python :: 3.8
Classifier: Programming Language :: Python :: 3.9
Classifier: Programming Language :: Python :: 3.10
Classifier: Programming Language :: Python :: 3.11
Classifier: Programming Language :: Python :: Implementation :: CPython
Classifier: Programming Language :: Python :: Implementation :: PyPy
Requires-Python: >=3.8
Requires-Dist: databind<4.5.0
Requires-Dist: pydoc-markdown==4.8.2
Requires-Dist: requests
Requires-Dist: setuptools
